ar/__init__.py
ar/ttm.zip
pysrcdist-0.0.6.dist-info/LICENSE.txt
pysrcdist-0.0.6.dist-info/METADATA
pysrcdist-0.0.6.dist-info/WHEEL
pysrcdist-0.0.6.dist-info/top_level.txt
pysrcdist-0.0.6.dist-info/RECORD
