Metadata-Version: 2.1
Name: pysrcdist
Version: 0.0.6
Summary: source code
Home-page: https://github.com/LunAnalects/pysrcdist
Author: Lunzhao
Author-email: Lunzhao <lunanalects@outlook.com>
Project-URL: Homepage, https://github.com/LunAnalects/pysrcdist
Project-URL: Bug Tracker, https://github.com/LunAnalects/pysrcdist/issues
Classifier: Programming Language :: Python :: 3
Classifier: License :: OSI Approved :: MIT License
Classifier: Operating System :: OS Independent
Requires-Python: >=3.9, <4
License-File: LICENSE.txt
